alibaba_cloud_secretsmanager_client/__init__.py
alibaba_cloud_secretsmanager_client/cache_client_builder.py
alibaba_cloud_secretsmanager_client/secret_manager_cache_client.py
alibaba_cloud_secretsmanager_client/secret_manager_cache_client_builder.py
alibaba_cloud_secretsmanager_client/auth/__init__.py
alibaba_cloud_secretsmanager_client/auth/client_key_signer.py
alibaba_cloud_secretsmanager_client/cache/__init__.py
alibaba_cloud_secretsmanager_client/cache/cache_secret_store_strategy.py
alibaba_cloud_secretsmanager_client/cache/default_secret_cache_hook.py
alibaba_cloud_secretsmanager_client/cache/file_cache_secret_store_strategy.py
alibaba_cloud_secretsmanager_client/cache/memory_cache_secret_store_strategy.py
alibaba_cloud_secretsmanager_client/cache/secret_cache_hook.py
alibaba_cloud_secretsmanager_client/model/__init__.py
alibaba_cloud_secretsmanager_client/model/client_key_credentials.py
alibaba_cloud_secretsmanager_client/model/credentials_properties.py
alibaba_cloud_secretsmanager_client/model/dkms_config.py
alibaba_cloud_secretsmanager_client/model/region_info.py
alibaba_cloud_secretsmanager_client/model/secret_info.py
alibaba_cloud_secretsmanager_client/service/__init__.py
alibaba_cloud_secretsmanager_client/service/back_off_strategy.py
alibaba_cloud_secretsmanager_client/service/default_refresh_secret_strategy.py
alibaba_cloud_secretsmanager_client/service/default_secret_manager_client_builder.py
alibaba_cloud_secretsmanager_client/service/full_jitter_back_off_strategy.py
alibaba_cloud_secretsmanager_client/service/refresh_secret_strategy.py
alibaba_cloud_secretsmanager_client/service/secret_manager_client.py
alibaba_cloud_secretsmanager_client/service/user_agent_manager.py
alibaba_cloud_secretsmanager_client/utils/__init__.py
alibaba_cloud_secretsmanager_client/utils/aes_utils.py
alibaba_cloud_secretsmanager_client/utils/backoff_utils.py
alibaba_cloud_secretsmanager_client/utils/byte_buffer_utils.py
jepson_aliyun_secret_manager_client-0.1.5.dist-info/LICENSE
jepson_aliyun_secret_manager_client-0.1.5.dist-info/METADATA
jepson_aliyun_secret_manager_client-0.1.5.dist-info/WHEEL
jepson_aliyun_secret_manager_client-0.1.5.dist-info/top_level.txt
jepson_aliyun_secret_manager_client-0.1.5.dist-info/RECORD
