Metadata-Version: 2.1
Name: jepson-aliyun-secret-manager-client
Version: 0.1.5
Summary: Alibaba Cloud Secrets Manager Client implementation for Python
Author: Alibaba Cloud
Maintainer: Alibaba Cloud
License: Apache License 2.0
Keywords: aliyun,kms,secrets-manager
Classifier: Development Status :: 5 - Production/Stable
Classifier: Programming Language :: Python
Classifier: Programming Language :: Python :: 2
Classifier: Programming Language :: Python :: 2.7
Classifier: Programming Language :: Python :: 3
Classifier: Programming Language :: Python :: 3.4
Classifier: Programming Language :: Python :: 3.5
Classifier: Programming Language :: Python :: 3.6
Classifier: Programming Language :: Python :: 3.7
Classifier: Programming Language :: Python :: 3.8
Classifier: Programming Language :: Python :: 3.9
Classifier: Programming Language :: Python :: Implementation :: CPython
Classifier: Topic :: Security
License-File: LICENSE
Requires-Dist: aliyun-python-sdk-core >=2.13.30
Requires-Dist: aliyun-python-sdk-kms >=2.14.0
Requires-Dist: cryptography >=3.2.1
Requires-Dist: apscheduler ==3.11.0
Requires-Dist: bytebuffer >=0.1.0
Requires-Dist: pyopenssl >=16.2.0
Requires-Dist: alibabacloud-dkms-gcs-python2 ==1.0.4 ; python_version < "3"
Requires-Dist: alibabacloud-dkms-transfer-python2 ==0.1.3 ; python_version < "3"
Requires-Dist: protobuf <=3.17.0 ; python_version <= "3.6"
Requires-Dist: futures ; python_version == "2.7"
Requires-Dist: cryptography <=3.3.2 ; python_version == "2.7"
Requires-Dist: pyopenssl <=21.0.0 ; python_version == "2.7"
Requires-Dist: typing-extensions <=3.10.0.2 ; python_version == "2.7"
Requires-Dist: alibabacloud-dkms-transfer-python ==0.1.2 ; python_version > "3"
Requires-Dist: alibabacloud-dkms-gcs ==1.0.2 ; python_version >= "3"
Requires-Dist: cryptography <=38.0.3 ; python_version >= "3"
Requires-Dist: multidict <=5.1.0 ; python_version >= "3"
Requires-Dist: typing-extensions >=4.1.1 ; python_version >= "3"
Requires-Dist: protobuf <=3.20.2 ; python_version >= "3.7"
